importable/__init__.py
importable/importable.py
importable-0.2.2.dist-info/DESCRIPTION.rst
importable-0.2.2.dist-info/METADATA
importable-0.2.2.dist-info/RECORD
importable-0.2.2.dist-info/WHEEL
importable-0.2.2.dist-info/metadata.json
importable-0.2.2.dist-info/top_level.txt
