Metadata-Version: 2.0
Name: importable
Version: 0.2.2
Summary: Allows to import zip-compressed Python package by URL (http, hdfs).
Home-page: https://github.com/malexer/importable
Author: Alex (Oleksii) Markov
Author-email: alex@markovs.me
License: MIT
Keywords: import url http hdfs zip importable python_path
Platform: UNKNOWN
Classifier: Development Status :: 4 - Beta
Classifier: Intended Audience :: Developers
Classifier: Topic :: Software Development :: Libraries :: Python Modules
Classifier: License :: OSI Approved :: MIT License
Classifier: Programming Language :: Python :: 3.5
Classifier: Programming Language :: Python :: 3.6
Requires-Dist: hdfs
Requires-Dist: requests
